MANIFEST.in
README.md
setup.py
debian/README.Debian
debian/changelog
debian/compat
debian/control
debian/copyright
debian/python-specfor.docs
debian/python-specfor.install
debian/python3-specfor.docs
debian/python3-specfor.install
debian/rules
debian/source/format
doc/specs/specs.for_expectation.md
doc/specs/specs.for_match_plugin.md
doc/specs/specs.for_mock.md
doc/specs/specs.for_mock_call.md
doc/specs/specs.for_mock_ordered.md
doc/specs/specs.for_mock_plugin.md
doc/specs/specs.for_nil.md
doc/specs/specs.for_spec.md
doc/specs/specs.md
examples/__init__.py
examples/first.py
examples/mock.py
examples/separation.py
examples/sum_spec.py
python_specfor.egg-info/PKG-INFO
python_specfor.egg-info/SOURCES.txt
python_specfor.egg-info/dependency_links.txt
python_specfor.egg-info/top_level.txt
specfor/__init__.py
specfor/check.py
specfor/compat.py
specfor/doc.py
specfor/expectation.py
specfor/framework.py
specfor/match.py
specfor/walker.py
specfor/docs/__init__.py
specfor/docs/plugins.py
specfor/docs/simple.py
specfor/mockings/__init__.py
specfor/mockings/core.py
specfor/mockings/nil.py
specfor/mockings/plugins.py
specfor/mockings/util.py
specfor/mockings/restrictions/__init__.py
specfor/mockings/restrictions/args.py
specfor/mockings/restrictions/call.py
specfor/mockings/restrictions/ordered.py
specs/__init__.py
specs/for_expectation.py
specs/for_match_plugin.py
specs/for_mock.py
specs/for_mock_call.py
specs/for_mock_ordered.py
specs/for_mock_plugin.py
specs/for_nil.py
specs/for_spec.py