Metadata-Version: 1.0
Name: python-specfor
Version: 0.1.0
Summary: A Framework for Behavior Driven Development(BDD) based on stdlib's unittest
Home-page: http://github.com/bellbind/python-specfor
Author: bellbind
Author-email: bellbind@gmail.com
License: http://www.gnu.org/copyleft/lesser.html
Keywords: bdd,testing,unittest
Platform: UNKNOWN
Classifier: Development Status :: 1 - Planning
Classifier: Intended Audience :: Developers
Classifier: License :: OSI Approved :: GNU Library or Lesser General Public License (LGPL)
Classifier: Operating System :: OS Independent
Classifier: Programming Language :: Python
Classifier: Programming Language :: Python :: 2
Classifier: Programming Language :: Python :: 3
Classifier: Topic :: Software Development :: Testing
